opentelemetry/ext/honeycomb/sampling/__init__.py
opentelemetry/ext/honeycomb/sampling/conftest.py
opentelemetry/ext/honeycomb/sampling/version.py
opentelemetry_ext_honeycomb_samplers-0.3b0.dist-info/LICENSE
opentelemetry_ext_honeycomb_samplers-0.3b0.dist-info/METADATA
opentelemetry_ext_honeycomb_samplers-0.3b0.dist-info/WHEEL
opentelemetry_ext_honeycomb_samplers-0.3b0.dist-info/top_level.txt
opentelemetry_ext_honeycomb_samplers-0.3b0.dist-info/RECORD
