Metadata-Version: 2.1
Name: opentelemetry-ext-honeycomb-samplers
Version: 0.3b0
Summary: Honeycomb Samplers for OpenTelemetry
Home-page: https://github.com/honeycombio/opentelemetry-samplers-python
Author: Honeycomb Authors
Author-email: solutions@honeycomb.io
License: Apache-2.0
Platform: any
Classifier: Development Status :: 3 - Alpha
Classifier: Intended Audience :: Developers
Classifier: License :: OSI Approved :: Apache Software License
Classifier: Programming Language :: Python
Classifier: Programming Language :: Python :: 3
Classifier: Programming Language :: Python :: 3.4
Classifier: Programming Language :: Python :: 3.5
Classifier: Programming Language :: Python :: 3.6
Classifier: Programming Language :: Python :: 3.7
Requires-Python: >=3.4
Requires-Dist: opentelemetry-api (>=0.13b0)
Requires-Dist: opentelemetry-sdk (>=0.13b0)
Requires-Dist: libhoney (>=1.9.0)
